pylib_general/__init__.py
pylib_general/exceptions.py
pylib_general/num.py
pylib_general/properties.py
pylib_general/text.py
pylib_general-0.2.3.dist-info/LICENSE
pylib_general-0.2.3.dist-info/METADATA
pylib_general-0.2.3.dist-info/WHEEL
pylib_general-0.2.3.dist-info/top_level.txt
pylib_general-0.2.3.dist-info/RECORD
