Metadata-Version: 2.1
Name: pylib-general
Version: 0.2.3
Summary: general python features that may come in handy at some point.
Home-page: https://github.com/chronosirius/PyLib
Author: chronosirius
Author-email: author@example.com
License: UNKNOWN
Project-URL: Bug Tracker, https://github.com/chronosirius/PyLib/issues
Platform: UNKNOWN
Classifier: Programming Language :: Python :: 3
Classifier: License :: OSI Approved :: MIT License
Classifier: Operating System :: OS Independent
Requires-Python: >=3.8
License-File: LICENSE
